mambax/__init__.py
mambax/mamba.py
mambax/mamba2.py
mambax/pscan.py
mambax-0.4.1.dist-info/licenses/LICENSE
mambax-0.4.1.dist-info/METADATA
mambax-0.4.1.dist-info/WHEEL
mambax-0.4.1.dist-info/top_level.txt
mambax-0.4.1.dist-info/RECORD
