Metadata-Version: 2.4
Name: mambax
Version: 0.4.1
Summary: Optimized Mamba implementation with chunk processing and ONNX export
Author: Oleg Kufa
Author-email: os.schischkin@gmail.com
Project-URL: Source Code, https://github.com/yourusername/mambax
Project-URL: Bug Tracker, https://github.com/yourusername/mambax/issues
Keywords: mamba,pytorch,deep learning
Classifier: Programming Language :: Python :: 3.10
Classifier: Programming Language :: Python :: 3.11
Classifier: License :: OSI Approved :: MIT License
Classifier: Operating System :: OS Independent
Classifier: Intended Audience :: Science/Research
Classifier: Topic :: Scientific/Engineering :: Artificial Intelligence
Requires-Python: >=3.10
License-File: LICENSE
Requires-Dist: torch>=2.5.0
Requires-Dist: numpy>=1.21.0
Dynamic: author
Dynamic: author-email
Dynamic: classifier
Dynamic: description
Dynamic: description-content-type
Dynamic: keywords
Dynamic: license-file
Dynamic: project-url
Dynamic: requires-dist
Dynamic: requires-python
Dynamic: summary
